faust/streams.py
faust/auth.py
faust/channels.py
faust/windows.py
faust/topics.py
faust/events.py
faust/joins.py
faust/worker.py
faust/exceptions.py
faust/py.typed
faust/__main__.py
faust/__init__.py
faust/types/codecs.py
faust/types/sensors.py
faust/types/core.py
faust/types/fixups.py
faust/types/agents.py
faust/types/streams.py
faust/types/auth.py
faust/types/channels.py
faust/types/tuples.py
faust/types/windows.py
faust/types/topics.py
faust/types/events.py
faust/types/joins.py
faust/types/stores.py
faust/types/app.py
faust/types/enums.py
faust/types/_env.py
faust/types/tables.py
faust/types/web.py
faust/types/serializers.py
faust/types/assignor.py
faust/types/router.py
faust/types/transports.py
faust/types/__init__.py
faust/types/models.py
faust/types/settings/sections.py
faust/types/settings/params.py
faust/types/settings/base.py
faust/types/settings/settings.py
faust/types/settings/__init__.py
faust/utils/_iso8601_python.py
faust/utils/platforms.py
faust/utils/cron.py
faust/utils/venusian.py
faust/utils/iso8601.py
faust/utils/functional.py
faust/utils/agent_stopper.py
faust/utils/tracing.py
faust/utils/json.py
faust/utils/urls.py
faust/utils/codegen.py
faust/utils/__init__.py
faust/utils/terminal/spinners.py
faust/utils/terminal/tables.py
faust/utils/terminal/__init__.py
faust/utils/kafka/__init__.py
faust/utils/kafka/protocol/api.py
faust/utils/kafka/protocol/admin.py
faust/utils/kafka/protocol/__init__.py
faust/assignor/leader_assignor.py
faust/assignor/cluster_assignment.py
faust/assignor/copartitioned_assignor.py
faust/assignor/client_assignment.py
faust/assignor/partition_assignor.py
faust/assignor/__init__.py
faust/app/_attached.py
faust/app/base.py
faust/app/router.py
faust/app/__init__.py
faust/web/exceptions.py
faust/web/base.py
faust/web/blueprints.py
faust/web/views.py
faust/web/__init__.py
faust/web/apps/production_index.py
faust/web/apps/graph.py
wbarnha_faust_streaming-0.9.4rc3.dist-info/LICENSE
wbarnha_faust_streaming-0.9.4rc3.dist-info/AUTHORS.md
wbarnha_faust_streaming-0.9.4rc3.dist-info/top_level.txt
wbarnha_faust_streaming-0.9.4rc3.dist-info/WHEEL
wbarnha_faust_streaming-0.9.4rc3.dist-info/entry_points.txt
wbarnha_faust_streaming-0.9.4rc3.dist-info/RECORD
wbarnha_faust_streaming-0.9.4rc3.dist-info/METADATA
