Metadata-Version: 2.1
Name: wbarnha-faust-streaming
Version: 0.9.4rc3
Summary: Python Stream processing.
Home-page: https://github.com/faust-streaming/faust
Author: Robinhood Markets, Inc.
Author-email: schrohm@gmail.com, vpatki@wayfair.com, williambbarnhart@gmail.com
License: BSD 3-Clause
Project-URL: Bug Reports, https://github.com/faust-streaming/faust/issues
Project-URL: Source, https://github.com/faust-streaming/faust
Project-URL: Documentation, https://faust-streaming.github.io/faust
Keywords: stream,processing,asyncio,distributed,queue,kafka
Platform: any
Classifier: Framework :: AsyncIO
Classifier: Development Status :: 5 - Production/Stable
Classifier: Intended Audience :: Developers
Classifier: Natural Language :: English
Classifier: License :: OSI Approved :: BSD License
Classifier: Programming Language :: Python
Classifier: Programming Language :: Python :: 3 :: Only
Classifier: Programming Language :: Python :: 3.7
Classifier: Programming Language :: Python :: 3.8
Classifier: Programming Language :: Python :: 3.9
Classifier: Programming Language :: Python :: 3.10
Classifier: Programming Language :: Python :: Implementation :: CPython
Classifier: Programming Language :: Python :: Implementation :: PyPy
Classifier: Operating System :: POSIX
Classifier: Operating System :: POSIX :: Linux
Classifier: Operating System :: MacOS :: MacOS X
Classifier: Operating System :: POSIX :: BSD
Classifier: Operating System :: Microsoft :: Windows
Classifier: Topic :: System :: Networking
Classifier: Topic :: System :: Distributed Computing
Requires-Python: >=3.7.0
License-File: LICENSE
License-File: AUTHORS.md
Requires-Dist: aiohttp (<4.0,>=3.5.2)
Requires-Dist: aiohttp-cors (<2.0,>=0.7)
Requires-Dist: aiokafka (<0.8.0,>=0.7.1)
Requires-Dist: click (<8.2,>=6.7)
Requires-Dist: mode-streaming (>=0.2.0)
Requires-Dist: opentracing (<=2.4.0,>=1.3.0)
Requires-Dist: terminaltables (<4.0,>=3.1)
Requires-Dist: yarl (<2.0,>=1.0)
Requires-Dist: croniter (>=0.3.16)
Requires-Dist: mypy-extensions
Requires-Dist: venusian (==3.0.0)
Requires-Dist: intervaltree
Requires-Dist: six
Provides-Extra: aiodns
Requires-Dist: aiodns (>=1.1) ; extra == 'aiodns'
Provides-Extra: aiomonitor
Requires-Dist: aiomonitor (>=0.4.4) ; extra == 'aiomonitor'
Provides-Extra: cchardet
Requires-Dist: cchardet (>=2.1) ; extra == 'cchardet'
Provides-Extra: ciso8601
Requires-Dist: ciso8601 ; extra == 'ciso8601'
Provides-Extra: cython
Requires-Dist: cython ; extra == 'cython'
Provides-Extra: datadog
Requires-Dist: datadog ; extra == 'datadog'
Provides-Extra: debug
Requires-Dist: setproctitle (>=1.1) ; extra == 'debug'
Requires-Dist: aiomonitor (>=0.4.4) ; extra == 'debug'
Provides-Extra: eventlet
Requires-Dist: faust-aioeventlet ; extra == 'eventlet'
Requires-Dist: dnspython ; extra == 'eventlet'
Provides-Extra: fast
Requires-Dist: aiodns (>=1.1) ; extra == 'fast'
Requires-Dist: cchardet (>=2.1) ; extra == 'fast'
Requires-Dist: ciso8601 ; extra == 'fast'
Requires-Dist: cython ; extra == 'fast'
Requires-Dist: orjson (<4.0,>=2.0) ; extra == 'fast'
Requires-Dist: setproctitle (>=1.1) ; extra == 'fast'
Provides-Extra: orjson
Requires-Dist: orjson (<4.0,>=2.0) ; extra == 'orjson'
Provides-Extra: prometheus
Requires-Dist: prometheus-client ; extra == 'prometheus'
Provides-Extra: redis
Requires-Dist: aredis (<2.0,>=1.1.3) ; extra == 'redis'
Provides-Extra: rocksdb
Requires-Dist: faust-streaming-rocksdb (>=0.8.0) ; extra == 'rocksdb'
Provides-Extra: sentry
Requires-Dist: raven (<7.0,>=6.10.0) ; extra == 'sentry'
Requires-Dist: raven-aiohttp (>=0.7.0) ; extra == 'sentry'
Requires-Dist: sentry-sdk (>=0.7.10) ; extra == 'sentry'
Provides-Extra: setproctitle
Requires-Dist: setproctitle (>=1.1) ; extra == 'setproctitle'
Provides-Extra: statsd
Requires-Dist: statsd (~=3.3.0) ; extra == 'statsd'
Provides-Extra: uvloop
Requires-Dist: uvloop (>=0.8.1) ; extra == 'uvloop'
Provides-Extra: yaml
Requires-Dist: pyyaml (>=5.1) ; extra == 'yaml'
